dvoice_tts/__init__.py
dvoice_tts/tts.py
dvoice_tts-1.0.3.dist-info/licenses/LICENSE
dvoice_tts-1.0.3.dist-info/METADATA
dvoice_tts-1.0.3.dist-info/WHEEL
dvoice_tts-1.0.3.dist-info/top_level.txt
dvoice_tts-1.0.3.dist-info/RECORD
