Metadata-Version: 2.4
Name: dvoice-tts
Version: 1.0.3
Summary: Python client for DVoice TTS API
Home-page: https://github.com/khabib-developer/dvoice-tts-python
Author: Khabib Sharopov
Author-email: habibsharopov501@gmail.com
Classifier: Programming Language :: Python :: 3
Classifier: License :: OSI Approved :: MIT License
Requires-Python: >=3.6
License-File: LICENSE
Requires-Dist: requests
Requires-Dist: websocket-client
Dynamic: author
Dynamic: author-email
Dynamic: classifier
Dynamic: description
Dynamic: description-content-type
Dynamic: home-page
Dynamic: license-file
Dynamic: requires-dist
Dynamic: requires-python
Dynamic: summary
